rtl/fir_filter_folded.v
// fir_filter_folded.v
// 11-tap symmetric low-pass FIR using a folded architecture (HALF+1 = 6 multipliers
// instead of 11). Coefficients are Q8.8; the full impulse response sums to 256 (1.0),
// so the filter has unity DC gain. Single-cycle: a combinational folded multiply-
// accumulate over the delay line, registered once per clock.

module fir_filter_folded #(
    parameter DATA_WIDTH  = 16,   // Q8.8 samples
    parameter COEFF_WIDTH = 16,   // Q8.8 coefficients
    parameter TAPS        = 11,   // odd, symmetric
    parameter FRAC        = 8     // fractional bits (Q8.8)
)(
    input  wire                          clk,
    input  wire                          reset,    // synchronous, active high
    input  wire signed [DATA_WIDTH-1:0]  data_in,
    output reg  signed [DATA_WIDTH-1:0]  data_out
);
    localparam HALF = (TAPS-1)/2;     // 5 outer pairs + 1 center tap

    // Symmetric coefficients c[0..HALF], c[HALF] is the center. Q8.8.
    // Full 11-tap response = {c0,c1,c2,c3,c4,c5,c4,c3,c2,c1,c0}, sum = 256 -> unity DC gain.
    wire signed [COEFF_WIDTH-1:0] c [0:HALF];
    assign c[0] = 16'hFFFF;   //  -1
    assign c[1] = 16'hFFFE;   //  -2
    assign c[2] = 16'h0003;   //   3
    assign c[3] = 16'h001B;   //  27
    assign c[4] = 16'h003E;   //  62
    assign c[5] = 16'h004E;   //  78  (center)

    // Full delay line: x[0] = newest sample ... x[TAPS-1] = oldest.
    reg signed [DATA_WIDTH-1:0] x [0:TAPS-1];

    // Folded multiply-accumulate over the current delay line (combinational, blocking).
    // Pairing x[k] with x[TAPS-1-k] lets the symmetric taps share one multiplier.
    localparam ACC_WIDTH = DATA_WIDTH + COEFF_WIDTH + 4;   // headroom for the summed products
    reg signed [ACC_WIDTH-1:0] acc;
    integer k;
    always @(*) begin
        acc = $signed(c[HALF]) * $signed(x[HALF]);                          // center tap
        for (k = 0; k < HALF; k = k + 1)
            acc = acc + $signed(c[k]) * ($signed(x[k]) + $signed(x[TAPS-1-k]));
    end

    // Register the delay line and the scaled output once per clock.
    integer i;
    always @(posedge clk) begin
        if (reset) begin
            for (i = 0; i < TAPS; i = i + 1)
                x[i] <= {DATA_WIDTH{1'b0}};
            data_out <= {DATA_WIDTH{1'b0}};
        end else begin
            for (i = TAPS-1; i > 0; i = i - 1)
                x[i] <= x[i-1];
            x[0] <= data_in;
            data_out <= acc >>> FRAC;     // Q16.16 product-sum back to Q8.8
        end
    end
endmodule

testbench/fir_filter_folded_tb.v
// fir_filter_folded_tb.v
// Self-checking testbench. Verifies:
//   1. unity DC gain: a held 1.0 input settles to a 1.0 output
//   2. impulse response is symmetric and sums to 1.0 (linear-phase, unity gain)
// Prints RESULT: PASS only if every check holds.

`timescale 1ns/1ps

module fir_filter_folded_tb;
    localparam TAPS = 11;

    reg                clk = 0;
    reg                reset = 1;
    reg  signed [15:0] data_in = 0;
    wire signed [15:0] data_out;

    integer i, s, isum, errors = 0;
    reg signed [15:0] resp [0:TAPS-1];

    fir_filter_folded dut (.clk(clk), .reset(reset), .data_in(data_in), .data_out(data_out));

    always #5 clk = ~clk;

    initial begin
        $dumpfile("fir_filter_folded.vcd");
        $dumpvars(0, fir_filter_folded_tb);
        $display("=== FIR Filter (folded) self-checking test ===");

        // Reset
        @(negedge clk); @(negedge clk); reset = 0;

        // Test 1: unity DC gain
        data_in = 16'sh0100;                 // 1.0 in Q8.8
        repeat (TAPS+4) @(negedge clk);
        if (data_out >= 16'sh00FF && data_out <= 16'sh0101)
            $display("PASS Test 1 (unity DC gain): data_out = %0d (expected 256)", data_out);
        else begin
            errors = errors + 1;
            $display("FAIL Test 1 (unity DC gain): data_out = %0d (expected 256)", data_out);
        end

        // Test 2: impulse response symmetry and sum
        reset = 1; @(negedge clk); @(negedge clk); reset = 0;
        data_in = 16'sh0100;                 // one-cycle impulse
        @(negedge clk);
        data_in = 0;
        for (s = 0; s < TAPS; s = s + 1) begin
            @(negedge clk);
            resp[s] = data_out;              // 1-cycle latency captured across TAPS samples
        end
        for (i = 0; i < TAPS; i = i + 1)
            if (resp[i] !== resp[TAPS-1-i]) begin
                errors = errors + 1;
                $display("FAIL Test 2 (symmetry): resp[%0d]=%0d != resp[%0d]=%0d",
                         i, resp[i], TAPS-1-i, resp[TAPS-1-i]);
            end
        isum = 0;
        for (i = 0; i < TAPS; i = i + 1) isum = isum + resp[i];
        if (isum === 256)
            $display("PASS Test 2 (impulse symmetric, sum = %0d)", isum);
        else begin
            errors = errors + 1;
            $display("FAIL Test 2 (impulse sum = %0d, expected 256)", isum);
        end

        if (errors == 0) $display("RESULT: PASS (all checks)");
        else             $display("RESULT: FAIL (%0d errors)", errors);
        #20 $finish;
    end
endmodule

fir_filter_folded.vcd
$date
	Wed Jul 01 18:44:00 2026
$end
$version
	Icarus Verilog
$end
$timescale
	1ps
$end
$scope module fir_filter_folded_tb $end
$var wire 16 ! data_out [15:0] $end
$var parameter 32 " TAPS $end
$var reg 1 # clk $end
$var reg 16 $ data_in [15:0] $end
$var reg 1 % reset $end
$var integer 32 & errors [31:0] $end
$var integer 32 ' i [31:0] $end
$var integer 32 ( isum [31:0] $end
$var integer 32 ) s [31:0] $end
$scope module dut $end
$var wire 1 # clk $end
$var wire 16 * data_in [15:0] $end
$var wire 1 % reset $end
$var parameter 34 + ACC_WIDTH $end
$var parameter 32 , COEFF_WIDTH $end
$var parameter 32 - DATA_WIDTH $end
$var parameter 32 . FRAC $end
$var parameter 33 / HALF $end
$var parameter 32 0 TAPS $end
$var reg 36 1 acc [35:0] $end
$var reg 16 2 data_out [15:0] $end
$var integer 32 3 i [31:0] $end
$var integer 32 4 k [31:0] $end
$upscope $end
$upscope $end
$enddefinitions $end
$comment Show the parameter values. $end
$dumpall
b1011 0
b101 /
b1000 .
b10000 -
b10000 ,
b100100 +
b1011 "
$end
#0
$dumpvars
b101 4
bx 3
bx 2
bx 1
b0 *
bx )
bx (
bx '
b0 &
1%
b0 $
0#
bx !
$end
#5000
b101 4
b0 1
b0 !
b0 2
b1011 3
1#
#10000
0#
#15000
b1011 3
1#
#20000
b100000000 $
b100000000 *
0%
0#
#25000
b111111111111111111111111111100000000 1
b101 4
b0 3
1#
#30000
0#
#35000
b101 4
b111111111111111111111111110100000000 1
b1111111111111111 !
b1111111111111111 2
b0 3
1#
#40000
0#
#45000
b101 4
b0 1
b1111111111111101 !
b1111111111111101 2
b0 3
1#
#50000
0#
#55000
b1101100000000 1
b101 4
b0 !
b0 2
b0 3
1#
#60000
0#
#65000
b101 4
b101100100000000 1
b11011 !
b11011 2
b0 3
1#
#70000
0#
#75000
b101 4
b1010011100000000 1
b1011001 !
b1011001 2
b0 3
1#
#80000
0#
#85000
b101 4
b1110010100000000 1
b10100111 !
b10100111 2
b0 3
1#
#90000
0#
#95000
b101 4
b10000000000000000 1
b11100101 !
b11100101 2
b0 3
1#
#100000
0#
#105000
b101 4
b10000001100000000 1
b100000000 !
b100000000 2
b0 3
1#
#110000
0#
#115000
b101 4
b10000000100000000 1
b100000011 !
b100000011 2
b0 3
1#
#120000
0#
#125000
b101 4
b10000000000000000 1
b100000001 !
b100000001 2
b0 3
1#
#130000
0#
#135000
b100000000 !
b100000000 2
b0 3
1#
#140000
0#
#145000
b0 3
1#
#150000
0#
#155000
b0 3
1#
#160000
0#
#165000
b0 3
1#
#170000
1%
0#
#175000
b101 4
b0 1
b0 !
b0 2
b1011 3
1#
#180000
0#
#185000
b1011 3
1#
#190000
0%
0#
#195000
b111111111111111111111111111100000000 1
b101 4
b0 3
1#
#200000
b0 )
b0 $
b0 *
0#
#205000
b101 4
b111111111111111111111111111000000000 1
b1111111111111111 !
b1111111111111111 2
b0 3
1#
#210000
b1 )
0#
#215000
b101 4
b1100000000 1
b1111111111111110 !
b1111111111111110 2
b0 3
1#
#220000
b10 )
0#
#225000
b101 4
b1101100000000 1
b11 !
b11 2
b0 3
1#
#230000
b11 )
0#
#235000
b101 4
b11111000000000 1
b11011 !
b11011 2
b0 3
1#
#240000
b100 )
0#
#245000
b101 4
b100111000000000 1
b111110 !
b111110 2
b0 3
1#
#250000
b101 )
0#
#255000
b101 4
b11111000000000 1
b1001110 !
b1001110 2
b0 3
1#
#260000
b110 )
0#
#265000
b101 4
b1101100000000 1
b111110 !
b111110 2
b0 3
1#
#270000
b111 )
0#
#275000
b101 4
b1100000000 1
b11011 !
b11011 2
b0 3
1#
#280000
b1000 )
0#
#285000
b101 4
b111111111111111111111111111000000000 1
b11 !
b11 2
b0 3
1#
#290000
b1001 )
0#
#295000
b101 4
b111111111111111111111111111100000000 1
b1111111111111110 !
b1111111111111110 2
b0 3
1#
#300000
b1010 )
0#
#305000
b101 4
b0 1
b1111111111111111 !
b1111111111111111 2
b0 3
1#
#310000
b100000000 (
b1011 '
b1011 )
0#
#315000
b0 !
b0 2
b0 3
1#
#320000
0#
#325000
b0 3
1#
