rtl/fir_filter_folded.v
module fir_filter_folded #(
  parameter ORDER = 10,          // 11-tap filter
  parameter COEFFICIENTS_WIDTH = 16,
  parameter DATA_WIDTH = 16
)(
  input wire clk,
  input wire reset,
  input wire signed [DATA_WIDTH-1:0] data_in,
  output reg signed [DATA_WIDTH-1:0] data_out
);

  // Coefficient storage (only need half + center due to folded structure)
  wire signed [COEFFICIENTS_WIDTH-1:0] coefficients [0:ORDER/2];
  assign coefficients[0] = 16'hFFEA;
  assign coefficients[1] = 16'h0009;
  assign coefficients[2] = 16'h0019;
  assign coefficients[3] = 16'h002D;
  assign coefficients[4] = 16'h003D;
  assign coefficients[5] = 16'h0043;  // The center coefficient (h[5])

  // Shift register (stores ORDER/2 + 1 samples)
  reg signed [DATA_WIDTH-1:0] shift_reg [0:ORDER/2];
  integer i;
  
  always @(posedge clk) begin
    if (reset) begin
      for (i=0; i<=ORDER/2; i=i+1) 
        shift_reg[i] <= 0;
    end else begin
      // Shift data through the register
      shift_reg[0] <= data_in;
      for (i=1; i<=ORDER/2; i=i+1)
        shift_reg[i] <= shift_reg[i-1];
    end
  end

  // Folded MAC operation with proper accumulation
  reg signed [DATA_WIDTH+COEFFICIENTS_WIDTH:0] acc;  // Extra bit for overflow
  reg signed [DATA_WIDTH-1:0] sum_symmetric [0:ORDER/2-1];
  
  always @(posedge clk) begin
    if (reset) begin
      acc <= 0;
      data_out <= 0;
      for (i=0; i<ORDER/2; i=i+1)
        sum_symmetric[i] <= 0;
    end else begin
      // Pre-calculate the symmetric pairs
      for (i=0; i<ORDER/2; i=i+1)
        sum_symmetric[i] <= shift_reg[i] + shift_reg[ORDER/2 - i];
      
      // Initialize with the center tap
      acc <= $signed(coefficients[ORDER/2]) * $signed(shift_reg[ORDER/2]);
      
      // Accumulate the symmetric taps
      for (i=0; i<ORDER/2; i=i+1)
        acc <= acc + ($signed(coefficients[i]) * $signed(sum_symmetric[i]));
      
      // Output with rounding
      data_out <= acc[23:8];  // Q8.8 output
    end
  end
endmodule

testbenches/fir_filter_folded_tb.v
`timescale 1ns/1ps

module fir_filter_folded_tb;
  reg clk, reset;
  reg signed [15:0] data_in;
  wire signed [15:0] data_out;

  // Instantiate DUT
  fir_filter_folded dut (clk, reset, data_in, data_out);

  // Clock generation (100 MHz)
  always #5 clk = ~clk;

  // Test sequence
  initial begin
    // Initialize
    clk = 0; reset = 1; data_in = 0;
    #20 reset = 0;
    #10; // Wait one clock after reset

    // Test 1: Impulse Response (just check first output)
    data_in = 16'h0100; // 1.0 in Q8.8
    #10;
    data_in = 0;
    #100; // Wait for output
    $display("First output: ", data_out);

    // Test 2: Simple step response (visual check)
    repeat (5) begin
      data_in = 16'h0100; // Step input
      #10;
    end
    data_in = 0;
    #100;

    // Test 3: Quick symmetric check
    data_in = 100;  #20;
    data_in = -100; #20;
    $display("Symmetric test output: ", data_out);

    // Test 4: Show some outputs
    data_in = 16'h2000; #20;
    data_in = 16'h4000; #20;
    data_in = 16'h0000; #20;

    $display("Done. Check waveforms for behavior.");
    #100;
    $finish;
  end

  // Save waveforms
  initial begin
    $dumpfile("fir_filter_folded.vcd");
    $dumpvars(0, fir_filter_folded_tb);
  end
endmodule

results/fir_filter_folded.vcd
$date
	Mon May 26 01:05:23 2025
$end
$version
	Icarus Verilog
$end
$timescale
	1ps
$end
$scope module fir_filter_folded_tb $end
$var wire 16 ! data_out [15:0] $end
$var reg 1 " clk $end
$var reg 16 # data_in [15:0] $end
$var reg 1 $ reset $end
$scope module dut $end
$var wire 1 " clk $end
$var wire 16 % data_in [15:0] $end
$var wire 1 $ reset $end
$var parameter 32 & COEFFICIENTS_WIDTH $end
$var parameter 32 ' DATA_WIDTH $end
$var parameter 32 ( ORDER $end
$var reg 33 ) acc [32:0] $end
$var reg 16 * data_out [15:0] $end
$var integer 32 + i [31:0] $end
$upscope $end
$upscope $end
$enddefinitions $end
$comment Show the parameter values. $end
$dumpall
b1010 (
b10000 '
b10000 &
$end
#0
$dumpvars
bx +
bx *
bx )
b0 %
1$
b0 #
0"
bx !
$end
#5000
b0 !
b0 *
b0 )
b110 +
1"
#10000
0"
#15000
b101 +
1"
#20000
0"
0$
#25000
b110 +
1"
#30000
0"
b100000000 #
b100000000 %
#35000
b101 +
1"
#40000
0"
b0 #
b0 %
#45000
b110 +
1"
#50000
0"
#55000
b0 )
b101 +
1"
#60000
0"
#65000
b11110100000000 )
b110 +
1"
#70000
0"
#75000
b111101 !
b111101 *
b11110100000000 )
b101 +
1"
#80000
0"
#85000
b11110100000000 )
b110 +
1"
#90000
0"
#95000
b111101000000000 )
b101 +
1"
#100000
0"
#105000
b1111010 !
b1111010 *
b111101000000000 )
b110 +
1"
#110000
0"
#115000
b111101000000000 )
b101 +
1"
#120000
0"
#125000
b111101000000000 )
b110 +
1"
#130000
0"
#135000
b111101000000000 )
b101 +
1"
#140000
0"
b100000000 #
b100000000 %
#145000
b111101000000000 )
b110 +
1"
#150000
0"
#155000
b111101000000000 )
b101 +
1"
#160000
0"
#165000
b111101000000000 )
b110 +
1"
#170000
0"
#175000
b1011011100000000 )
b101 +
1"
#180000
0"
#185000
b10110111 !
b10110111 *
b1111010000000000 )
b110 +
1"
#190000
0"
b0 #
b0 %
#195000
b11110100 !
b11110100 *
b10011000100000000 )
b101 +
1"
#200000
0"
#205000
b100110001 !
b100110001 *
b11010101100000000 )
b110 +
1"
#210000
0"
#215000
b110101011 !
b110101011 *
b100010010100000000 )
b101 +
1"
#220000
0"
#225000
b1000100101 !
b1000100101 *
b100110001000000000 )
b110 +
1"
#230000
0"
#235000
b1001100010 !
b1001100010 *
b101001111100000000 )
b101 +
1"
#240000
0"
#245000
b1010011111 !
b1010011111 *
b101101110000000000 )
b110 +
1"
#250000
0"
#255000
b1011011100 !
b1011011100 *
b101101110000000000 )
b101 +
1"
#260000
0"
#265000
b101101110000000000 )
b110 +
1"
#270000
0"
#275000
b101101110000000000 )
b101 +
1"
#280000
0"
#285000
b101101110000000000 )
b110 +
1"
#290000
0"
b1100100 #
b1100100 %
#295000
b101101110000000000 )
b101 +
1"
#300000
0"
#305000
b101101110000000000 )
b110 +
1"
#310000
0"
b1111111110011100 #
b1111111110011100 %
#315000
b101101110000000000 )
b101 +
1"
#320000
0"
#325000
b101111001111010100 )
b110 +
1"
#330000
0"
b10000000000000 #
b10000000000000 %
#335000
b1011110011 !
b1011110011 *
b110000101110101000 )
b101 +
1"
#340000
0"
#345000
b1100001011 !
b1100001011 *
b101111001111010100 )
b110 +
1"
#350000
0"
b100000000000000 #
b100000000000000 %
#355000
b1011110011 !
b1011110011 *
b101111001111010100 )
b101 +
1"
#360000
0"
#365000
b10101010101110101000 )
b110 +
1"
#370000
0"
b0 #
b0 %
#375000
b101010101011 !
b101010101011 *
b100100011001111010100 )
b101 +
1"
#380000
0"
#385000
b1001000110011 !
b1001000110011 *
b1000010101110000000000 )
b110 +
1"
#390000
0"
#395000
b10000101011100 !
b10000101011100 *
b1110000011110000000000 )
b101 +
1"
#400000
0"
#405000
b11100000111100 !
b11100000111100 *
b1111111101110000000000 )
b110 +
1"
#410000
0"
#415000
b11111111011100 !
b11111111011100 *
b10011110001110000000000 )
b101 +
1"
#420000
0"
#425000
b100111100011100 !
b100111100011100 *
b10111100101110000000000 )
b110 +
1"
#430000
0"
#435000
b101111001011100 !
b101111001011100 *
b10111100101110000000000 )
b101 +
1"
#440000
0"
#445000
b10111100101110000000000 )
b110 +
1"
#450000
0"
#455000
b10111100101110000000000 )
b101 +
1"
#460000
0"
#465000
b10111100101110000000000 )
b110 +
1"
#470000
0"
#475000
b10111100101110000000000 )
b101 +
1"
#480000
0"
#485000
b10111100101110000000000 )
b110 +
1"
